[
  {
    "orderId": "1",
    "orderName": "Order Name #1",
    "items": [
      {
        "itemId": 1,
        "itemName": "Item Name #1",
        "price": 2.99,
        "quantity": 3
      },
      {
        "itemId": 2,
        "itemName": "Item Name #2",
        "price": 1.99,
        "quantity": 2
      }
    ]
  },
  {
    "orderId": "2",
    "orderName": "Order Name #2",
    "items": [
      {
        "itemId": 3,
        "itemName": "Item Name #3",
        "price": 3.99,
        "quantity": 5
      },
      {
        "itemId": 4,
        "itemName": "Item Name #4",
        "price": 4.99,
        "quantity": 9
      }
    ]
  }
]
